GAAPItoDB/__init__.py
GACustomReportEmailToDB/GACustomReportParcelasClicadas.py
GACustomReportEmailToDB/__init__.py
GACustomReportEmailToDB/__main__.py
GoogleAnalyticsETL-0.6.0.data/data/share/GoogleAnalyticsETL/examples/GABradescoSegurosToDB.py
GoogleAnalyticsETL-0.6.0.data/data/share/GoogleAnalyticsETL/examples/etl-by-email.py
GoogleAnalyticsETL-0.6.0.data/data/share/GoogleAnalyticsETL/examples/etl.py
GoogleAnalyticsETL-0.6.0.data/data/share/GoogleAnalyticsETL/examples/sources.conf.example
GoogleAnalyticsETL-0.6.0.dist-info/METADATA
GoogleAnalyticsETL-0.6.0.dist-info/WHEEL
GoogleAnalyticsETL-0.6.0.dist-info/top_level.txt
GoogleAnalyticsETL-0.6.0.dist-info/RECORD
