Metadata-Version: 2.1
Name: GoogleAnalyticsETL
Version: 0.6.0
Summary: Ingest a set of Google Analytics dimensions and put the data into a SQL table; can be run regularly to sync updates incrementally to DB
Home-page: https://github.com/avibrazil/GoogleAnalytics-ETL
Author: Avi Alkalay
Author-email: avibrazil@gmail.com
License: UNKNOWN
Platform: UNKNOWN
Classifier: Programming Language :: Python :: 3
Classifier: Operating System :: OS Independent
Classifier: Development Status :: 4 - Beta
Classifier: Environment :: Console
Classifier: Intended Audience :: Developers
Classifier: Intended Audience :: End Users/Desktop
Classifier: Intended Audience :: Information Technology
Classifier: License :: OSI Approved :: GNU Library or Lesser General Public License (LGPL)
Classifier: Operating System :: POSIX
Classifier: Topic :: Database
Classifier: Topic :: Software Development :: Libraries :: Python Modules
Classifier: Topic :: Internet
Requires-Python: >=3.6
Requires-Dist: sqlalchemy
Requires-Dist: pandas
Requires-Dist: oauth2client
Requires-Dist: google-api-python-client
Requires-Dist: python-dateutil
